cheigsfera/__init__.py
cheigsferaw-1.3.0.dist-info/METADATA
cheigsferaw-1.3.0.dist-info/WHEEL
cheigsferaw-1.3.0.dist-info/top_level.txt
cheigsferaw-1.3.0.dist-info/RECORD
