Metadata-Version: 2.2
Name: cheigsferaw
Version: 1.3.0
Summary: Пример пакета с зависимостями
Author: cheigg
Author-email: egorleuchin99@gmail.com
Requires-Dist: requests>=2.25.1
Requires-Dist: numpy>=1.19.5; python_version < "3.8"
Provides-Extra: dev
Requires-Dist: pytest>=6.0; extra == "dev"
